artifacta/__init__.py
artifacta/artifacts.py
artifacta/autolog.py
artifacta/context.py
artifacta/emitter.py
artifacta/metadata.py
artifacta/monitor.py
artifacta/primitives.py
artifacta/run.py
artifacta/utils.py
artifacta/integrations/__init__.py
artifacta/integrations/base.py
artifacta/integrations/dataset_utils.py
artifacta/integrations/pytorch_lightning.py
artifacta/integrations/sklearn.py
artifacta/integrations/tensorflow.py
artifacta/integrations/xgboost.py
artifacta/metadata_extractors/__init__.py
artifacta/metadata_extractors/torch.py
artifacta-0.2.0.dist-info/licenses/LICENSE
artifacta_ui/__init__.py
artifacta_ui/index.html
artifacta_ui/dist/index.html
artifacta_ui/dist/assets/KaTeX_AMS-Regular-BQhdFMY1.woff2
artifacta_ui/dist/assets/KaTeX_AMS-Regular-DMm9YOAa.woff
artifacta_ui/dist/assets/KaTeX_AMS-Regular-DRggAlZN.ttf
artifacta_ui/dist/assets/KaTeX_Caligraphic-Bold-ATXxdsX0.ttf
artifacta_ui/dist/assets/KaTeX_Caligraphic-Bold-BEiXGLvX.woff
artifacta_ui/dist/assets/KaTeX_Caligraphic-Bold-Dq_IR9rO.woff2
artifacta_ui/dist/assets/KaTeX_Caligraphic-Regular-CTRA-rTL.woff
artifacta_ui/dist/assets/KaTeX_Caligraphic-Regular-Di6jR-x-.woff2
artifacta_ui/dist/assets/KaTeX_Caligraphic-Regular-wX97UBjC.ttf
artifacta_ui/dist/assets/KaTeX_Fraktur-Bold-BdnERNNW.ttf
artifacta_ui/dist/assets/KaTeX_Fraktur-Bold-BsDP51OF.woff
artifacta_ui/dist/assets/KaTeX_Fraktur-Bold-CL6g_b3V.woff2
artifacta_ui/dist/assets/KaTeX_Fraktur-Regular-CB_wures.ttf
artifacta_ui/dist/assets/KaTeX_Fraktur-Regular-CTYiF6lA.woff2
artifacta_ui/dist/assets/KaTeX_Fraktur-Regular-Dxdc4cR9.woff
artifacta_ui/dist/assets/KaTeX_Main-Bold-Cx986IdX.woff2
artifacta_ui/dist/assets/KaTeX_Main-Bold-Jm3AIy58.woff
artifacta_ui/dist/assets/KaTeX_Main-Bold-waoOVXN0.ttf
artifacta_ui/dist/assets/KaTeX_Main-BoldItalic-DxDJ3AOS.woff2
artifacta_ui/dist/assets/KaTeX_Main-BoldItalic-DzxPMmG6.ttf
artifacta_ui/dist/assets/KaTeX_Main-BoldItalic-SpSLRI95.woff
artifacta_ui/dist/assets/KaTeX_Main-Italic-3WenGoN9.ttf
artifacta_ui/dist/assets/KaTeX_Main-Italic-BMLOBm91.woff
artifacta-0.2.0.dist-info/METADATA
artifacta-0.2.0.dist-info/WHEEL
artifacta-0.2.0.dist-info/entry_points.txt
artifacta-0.2.0.dist-info/top_level.txt
artifacta-0.2.0.dist-info/RECORD
