Metadata-Version: 2.4
Name: artifacta
Version: 0.2.0
Summary: Universal experiment and artifact tracking — gain insights and optimize models with confidence
Author: Artifacta Contributors
License: Elastic License 2.0
Project-URL: Homepage, https://github.com/walkerbdev/artifacta
Project-URL: Documentation, https://github.com/walkerbdev/artifacta#readme
Project-URL: Repository, https://github.com/walkerbdev/artifacta
Project-URL: Issues, https://github.com/walkerbdev/artifacta/issues
Keywords: experiment-tracking,visualization,mlops,data-science
Classifier: Development Status :: 3 - Alpha
Classifier: Intended Audience :: Developers
Classifier: Intended Audience :: Science/Research
Classifier: License :: Other/Proprietary License
Classifier: Programming Language :: Python :: 3
Classifier: Programming Language :: Python :: 3.8
Classifier: Programming Language :: Python :: 3.9
Classifier: Programming Language :: Python :: 3.10
Classifier: Programming Language :: Python :: 3.11
Classifier: Programming Language :: Python :: 3.12
Classifier: Programming Language :: Python :: 3.13
Classifier: Topic :: Scientific/Engineering
Classifier: Topic :: Scientific/Engineering :: Artificial Intelligence
Classifier: Topic :: Software Development :: Libraries :: Python Modules
Requires-Python: >=3.8
License-File: LICENSE
Requires-Dist: click~=8.0
Requires-Dist: flask~=2.0
Requires-Dist: flask-cors~=3.0
Requires-Dist: pillow<11.0,>=9.0; python_version < "3.12"
Requires-Dist: pillow<11.0,>=10.0; python_version >= "3.12"
Requires-Dist: fastapi~=0.100
Requires-Dist: uvicorn~=0.23
Requires-Dist: python-multipart~=0.0.6
Requires-Dist: sqlalchemy~=2.0
Requires-Dist: numpy~=1.24
Requires-Dist: requests~=2.31
Requires-Dist: psutil~=5.9
Provides-Extra: dev
Requires-Dist: pytest~=7.0; extra == "dev"
Requires-Dist: ruff~=0.1; extra == "dev"
Requires-Dist: mypy~=1.0; extra == "dev"
Requires-Dist: pre-commit~=3.0; extra == "dev"
Requires-Dist: pydocstyle~=6.3; extra == "dev"
Requires-Dist: sphinx~=7.0; extra == "dev"
Requires-Dist: sphinx-rtd-theme~=2.0; extra == "dev"
Requires-Dist: sphinx-autodoc-typehints~=1.24; extra == "dev"
Requires-Dist: numpy~=1.24; extra == "dev"
Requires-Dist: matplotlib~=3.7; extra == "dev"
Requires-Dist: seaborn~=0.12; extra == "dev"
Requires-Dist: scikit-learn~=1.3; extra == "dev"
Requires-Dist: xgboost~=1.7; extra == "dev"
Requires-Dist: lightgbm~=4.0; extra == "dev"
Requires-Dist: requests~=2.31; extra == "dev"
Requires-Dist: sqlalchemy~=2.0; extra == "dev"
Requires-Dist: pytorch-lightning~=2.0; extra == "dev"
Requires-Dist: torch~=2.0; extra == "dev"
Requires-Dist: torchvision~=0.15; extra == "dev"
Requires-Dist: tensorflow<3.0,>=2.12; python_version < "3.12" and extra == "dev"
Requires-Dist: tensorflow<3.0,>=2.16; python_version >= "3.12" and extra == "dev"
Requires-Dist: reportlab~=4.0; extra == "dev"
Requires-Dist: bump-my-version~=0.26; extra == "dev"
Provides-Extra: video
Requires-Dist: av~=10.0; extra == "video"
Dynamic: license-file
